terraform.py
terraform_executor-0.13.5.data/data/lib/terraform_linux
terraform_executor-0.13.5.data/data/lib/terraform_windows.exe
terraform_executor-0.13.5.dist-info/LICENSE
terraform_executor-0.13.5.dist-info/METADATA
terraform_executor-0.13.5.dist-info/WHEEL
terraform_executor-0.13.5.dist-info/entry_points.txt
terraform_executor-0.13.5.dist-info/top_level.txt
terraform_executor-0.13.5.dist-info/RECORD
