Metadata-Version: 2.1
Name: terraform-executor
Version: 0.13.5
Summary: UNKNOWN
Home-page: https://github.com/gen5-tools/terraform-binary
Author: Naresh Surisetty
Author-email: naresh@naresh.co
License: Apache License Version 2.0
Platform: UNKNOWN
